{
  "project_info": {
    "project_number": "80341476742",
    "project_id": "movie-app-7ac18",
    "storage_bucket": "movie-app-7ac18.firebasestorage.app"
  },
  "client": [
    {
      "client_info": {
        "mobilesdk_app_id": "1:80341476742:android:9ae4e08b4710ed6cda3807",
        "android_client_info": {
          "package_name": "com.example.flixmovies"
        }
      },
      "oauth_client": [],
      "api_key": [
        {
          "current_key": "AIzaSyCl2fvwjvPMfJ2P3J2KoVfmiWhp8S0Bym0"
        }
      ],
      "services": {
        "appinvite_service": {
          "other_platform_oauth_client": []
        }
      }
    }
  ],
  "configuration_version": "1"
}